STVQC_thebiglmaoski/STVQC.py
STVQC_thebiglmaoski/__init__.py
STVQC_thebiglmaoski/train.py
STVQC_thebiglmaoski-0.0.8.dist-info/LICENSE
STVQC_thebiglmaoski-0.0.8.dist-info/METADATA
STVQC_thebiglmaoski-0.0.8.dist-info/WHEEL
STVQC_thebiglmaoski-0.0.8.dist-info/top_level.txt
STVQC_thebiglmaoski-0.0.8.dist-info/RECORD
